<?xml version="1.0" encoding="UTF-8"?>
<sv:node xmlns:sv="http://www.jcp.org/jcr/sv/1.0" sv:name="brokenlinks">
  <sv:property sv:name="jcr:primaryType" sv:type="Name">
    <sv:value>hipposys:module</sv:value>
  </sv:property>
  <sv:property sv:name="hipposys:className" sv:type="String">
    <sv:value>org.onehippo.cms7.brokenlinks.BrokenLinksCheckerDaemonModule</sv:value>
  </sv:property>
  <sv:node sv:name="hippo:moduleconfig">
    <sv:property sv:name="jcr:primaryType" sv:type="Name">
      <sv:value>hippo:handle</sv:value>
    </sv:property>
    <sv:node sv:name="hippo:moduleconfig">
      <sv:property sv:name="jcr:primaryType" sv:type="Name">
        <sv:value>brokenlinks:config</sv:value>
      </sv:property>
      <sv:property sv:name="jcr:mixinTypes" sv:type="Name">
        <sv:value>mix:referenceable</sv:value>
      </sv:property>
      <sv:property sv:name="enabled" sv:type="Boolean">
        <sv:value>false</sv:value>
      </sv:property>
      <sv:property sv:name="cronExpression" sv:type="String">
        <sv:value>0 0 2 * * ? *</sv:value>
      </sv:property>
      <sv:property sv:name="connectionTimeout" sv:type="Long">
        <sv:value>10000</sv:value>
      </sv:property>
      <sv:property sv:name="nrHttpThreads" sv:type="Long">
        <sv:value>10</sv:value>
      </sv:property>
      <sv:property sv:name="socketTimeout" sv:type="Long">
        <sv:value>10000</sv:value>
      </sv:property>
      <sv:property sv:name="startPath" sv:type="String">
        <sv:value>/content/documents</sv:value>
      </sv:property>
      <sv:property sv:name="urlExcludes" sv:type="String">
        <sv:value></sv:value>
      </sv:property>
    </sv:node>
  </sv:node>
</sv:node>
