<?xml version="1.0" encoding="UTF-8"?><sv:node xmlns:sv="http://www.jcp.org/jcr/sv/1.0" sv:name="hippoaddoncrispdemo">
  <sv:property sv:name="jcr:primaryType" sv:type="Name">
    <sv:value>hippogallery:stdAssetGallery</sv:value>
  </sv:property>
  <sv:property sv:name="jcr:mixinTypes" sv:type="Name" sv:multiple="true">
    <sv:value>mix:versionable</sv:value>
  </sv:property>
  <sv:property sv:name="jcr:uuid" sv:type="String">
    <sv:value>c2937dd2-8b7c-4257-9d00-57adef91d95b</sv:value>
  </sv:property>
  <sv:property sv:name="hippostd:foldertype" sv:type="String" sv:multiple="true">
    <sv:value>new-file-folder</sv:value>
  </sv:property>
  <sv:property sv:name="hippostd:gallerytype" sv:type="String" sv:multiple="true">
    <sv:value>hippogallery:exampleAssetSet</sv:value>
  </sv:property>
</sv:node>
