<?xml version="1.0" encoding="UTF-8"?>
<sv:node xmlns:sv="http://www.jcp.org/jcr/sv/1.0" sv:name="marketing-perspective">
  <sv:property sv:name="jcr:primaryType" sv:type="Name">
    <sv:value>frontend:plugin</sv:value>
  </sv:property>
  <sv:property sv:name="cluster.name" sv:type="String">
    <sv:value>marketing-perspective</sv:value>
  </sv:property>
  <sv:property sv:name="persona.list.width" sv:type="Long">
    <sv:value>216</sv:value>
  </sv:property>
  <sv:property sv:name="plugin.class" sv:type="String">
    <sv:value>org.onehippo.cms7.marketing.MarketingPerspective</sv:value>
  </sv:property>
  <sv:property sv:name="wicket.id" sv:type="String">
    <sv:value>service.tab</sv:value>
  </sv:property>
  <sv:node sv:name="layout.wireframe">
    <sv:property sv:name="jcr:primaryType" sv:type="Name">
      <sv:value>frontend:pluginconfig</sv:value>
    </sv:property>
    <sv:property sv:name="center" sv:type="String">
      <sv:value>id=marketing-perspective-center,body=marketing-perspective-center-body,scroll=false</sv:value>
    </sv:property>
    <sv:property sv:name="linked.with.parent" sv:type="Boolean">
      <sv:value>true</sv:value>
    </sv:property>
    <sv:property sv:name="root.id" sv:type="String">
      <sv:value>marketing-perspective-wrapper</sv:value>
    </sv:property>
    <sv:property sv:name="top" sv:type="String">
      <sv:value>id=marketing-perspective-top,body=marketing-perspective-top-body,height=24</sv:value>
    </sv:property>
    <sv:property sv:name="units" sv:type="String">
      <sv:value>center</sv:value>
    </sv:property>
  </sv:node>
</sv:node>
