<?xml version="1.0" encoding="UTF-8"?>
<sv:node sv:name="blog-catalog" xmlns:sv="http://www.jcp.org/jcr/sv/1.0">
  <sv:property sv:name="jcr:primaryType" sv:type="Name">
    <sv:value>hst:containeritempackage</sv:value>
  </sv:property>
  <sv:node sv:name="bloglist">
    <sv:property sv:name="jcr:primaryType" sv:type="Name">
      <sv:value>hst:containeritemcomponent</sv:value>
    </sv:property>
    <sv:property sv:name="hst:componentclassname" sv:type="String">
      <sv:value>org.onehippo.cms7.essentials.components.EssentialsBlogComponent</sv:value>
    </sv:property>
    <sv:property sv:name="hst:label" sv:type="String">
      <sv:value>Blog List</sv:value>
    </sv:property>
    <sv:property sv:name="hst:template" sv:type="String">
      <sv:value>blog.list.content</sv:value>
    </sv:property>
    <sv:property sv:name="hst:xtype" sv:type="String">
      <sv:value>HST.Item</sv:value>
    </sv:property>
  </sv:node>
  <sv:node sv:name="facets">
    <sv:property sv:name="jcr:primaryType" sv:type="Name">
      <sv:value>hst:containeritemcomponent</sv:value>
    </sv:property>
    <sv:property sv:name="hst:componentclassname" sv:type="String">
      <sv:value>org.onehippo.cms7.essentials.components.EssentialsFacetsComponent</sv:value>
    </sv:property>
    <sv:property sv:name="hst:label" sv:type="String">
      <sv:value>Facets</sv:value>
    </sv:property>
    <sv:property sv:name="hst:template" sv:type="String">
      <sv:value>facet.template</sv:value>
    </sv:property>
    <sv:property sv:name="hst:xtype" sv:type="String">
      <sv:value>HST.Item</sv:value>
    </sv:property>
  </sv:node>
</sv:node>
