<?xml version="1.0" encoding="UTF-8" standalone="no"?>
<!--
  Copyright 2008-2016 Hippo

  Licensed under the Apache License, Version 2.0 (the  "License");
  you may not use this file except in compliance with the License.
  You may obtain a copy of the License at

  http://www.apache.org/licenses/LICENSE-2.0

  Unless required by applicable law or agreed to in writing, software
  distributed under the License is distributed on an "AS IS"
  BASIS, WITHOUT WARRANTIES OR CONDITIONS OF ANY KIND, either express or implied.
  See the License for the specific language governing permissions and
  limitations under the License.
--><sv:node xmlns:sv="http://www.jcp.org/jcr/sv/1.0" sv:name="hippo:initialize">
  <sv:property sv:name="jcr:primaryType" sv:type="Name">
    <sv:value>hippo:initializefolder</sv:value>
  </sv:property>
  <sv:node sv:name="taxonomydemo">
    <sv:property sv:name="jcr:primaryType" sv:type="Name">
      <sv:value>hippo:initializeitem</sv:value>
    </sv:property>
    <sv:property sv:name="hippo:sequence" sv:type="Double">
      <sv:value>30150.0</sv:value>
    </sv:property>
    <sv:property sv:name="hippo:namespace" sv:type="String">
      <sv:value>http://www.hippoecm.org/hst/nt/taxonomydemo/1.2</sv:value>
    </sv:property>
    <sv:property sv:name="hippo:nodetypesresource" sv:type="String">
      <sv:value>taxonomy-demo-types.cnd</sv:value>
    </sv:property>
  </sv:node>
  <sv:node sv:name="taxonomydemo-namespace">
    <sv:property sv:name="jcr:primaryType" sv:type="Name">
      <sv:value>hippo:initializeitem</sv:value>
    </sv:property>
    <sv:property sv:name="hippo:sequence" sv:type="Double">
      <sv:value>30151.0</sv:value>
    </sv:property>
    <sv:property sv:name="hippo:contentresource" sv:type="String">
      <sv:value>taxonomy-demo-namespace.xml</sv:value>
    </sv:property>
    <sv:property sv:name="hippo:contentroot" sv:type="String">
      <sv:value>/hippo:namespaces</sv:value>
    </sv:property>
  </sv:node>
  <sv:node sv:name="taxonomydemo-localeproviderservice">
    <sv:property sv:name="jcr:primaryType" sv:type="Name">
      <sv:value>hippo:initializeitem</sv:value>
    </sv:property>
    <sv:property sv:name="hippo:sequence" sv:type="Double">
      <sv:value>30152.0</sv:value>
    </sv:property>
    <sv:property sv:name="hippo:contentresource" sv:type="String">
      <sv:value>localeproviderservice.xml</sv:value>
    </sv:property>
    <sv:property sv:name="hippo:contentroot" sv:type="String">
      <sv:value>/hippo:configuration/hippo:frontend/cms/cms-services</sv:value>
    </sv:property>
  </sv:node>
  <sv:node sv:name="hst-sites">
    <sv:property sv:name="jcr:primaryType" sv:type="Name">
      <sv:value>hippo:initializeitem</sv:value>
    </sv:property>
    <sv:property sv:name="hippo:sequence" sv:type="Double">
      <sv:value>30153.0</sv:value>
    </sv:property>
    <sv:property sv:name="hippo:contentresource" sv:type="String">
      <sv:value>hst-sites.xml</sv:value>
    </sv:property>
    <sv:property sv:name="hippo:contentroot" sv:type="String">
      <sv:value>/hst:hst</sv:value>
    </sv:property>
  </sv:node>
  <sv:node sv:name="taxonomydemo-hst-configurations">
    <sv:property sv:name="jcr:primaryType" sv:type="Name">
      <sv:value>hippo:initializeitem</sv:value>
    </sv:property>
    <sv:property sv:name="hippo:sequence" sv:type="Double">
      <sv:value>30154.0</sv:value>
    </sv:property>
    <sv:property sv:name="hippo:contentresource" sv:type="String">
      <sv:value>hst-configurations.xml</sv:value>
    </sv:property>
    <sv:property sv:name="hippo:contentroot" sv:type="String">
      <sv:value>/hst:hst</sv:value>
    </sv:property>
  </sv:node>
  <sv:node sv:name="default-ecm-content">
    <sv:property sv:name="jcr:primaryType" sv:type="Name">
      <sv:value>hippo:initializeitem</sv:value>
    </sv:property>
    <sv:property sv:name="hippo:sequence" sv:type="Double">
      <sv:value>30155.0</sv:value>
    </sv:property>
    <sv:property sv:name="hippo:contentresource" sv:type="String">
      <sv:value>default-ecm-content.xml</sv:value>
    </sv:property>
    <sv:property sv:name="hippo:contentroot" sv:type="String">
      <sv:value>/</sv:value>
    </sv:property>
  </sv:node>
  <sv:node sv:name="taxonomydemo-en-sitemap">
    <sv:property sv:name="jcr:primaryType" sv:type="Name">
      <sv:value>hippo:initializeitem</sv:value>
    </sv:property>
    <sv:property sv:name="hippo:sequence" sv:type="Double">
      <sv:value>30156.0</sv:value>
    </sv:property>
    <sv:property sv:name="hippo:contentresource" sv:type="String">
      <sv:value>hstconfiguration/taxonomydemo-en/sitemap.xml</sv:value>
    </sv:property>
    <sv:property sv:name="hippo:contentroot" sv:type="String">
      <sv:value>/hst:hst/hst:configurations/taxonomydemo-en</sv:value>
    </sv:property>
  </sv:node>
  <sv:node sv:name="taxonomydemo-en-sitemenus">
    <sv:property sv:name="jcr:primaryType" sv:type="Name">
      <sv:value>hippo:initializeitem</sv:value>
    </sv:property>
    <sv:property sv:name="hippo:sequence" sv:type="Double">
      <sv:value>30157.0</sv:value>
    </sv:property>
    <sv:property sv:name="hippo:contentresource" sv:type="String">
      <sv:value>hstconfiguration/taxonomydemo-en/sitemenus.xml</sv:value>
    </sv:property>
    <sv:property sv:name="hippo:contentroot" sv:type="String">
      <sv:value>/hst:hst/hst:configurations/taxonomydemo-en</sv:value>
    </sv:property>
  </sv:node>
  <sv:node sv:name="taxonomydemo-en-channel">
    <sv:property sv:name="jcr:primaryType" sv:type="Name">
      <sv:value>hippo:initializeitem</sv:value>
    </sv:property>
    <sv:property sv:name="hippo:sequence" sv:type="Double">
      <sv:value>30158.0</sv:value>
    </sv:property>
    <sv:property sv:name="hippo:contentresource" sv:type="String">
      <sv:value>hstconfiguration/taxonomydemo-en/channel.xml</sv:value>
    </sv:property>
    <sv:property sv:name="hippo:contentroot" sv:type="String">
      <sv:value>/hst:hst/hst:configurations/taxonomydemo-en</sv:value>
    </sv:property>
  </sv:node>
  <sv:node sv:name="taxonomydemo-fr-sitemap">
    <sv:property sv:name="jcr:primaryType" sv:type="Name">
      <sv:value>hippo:initializeitem</sv:value>
    </sv:property>
    <sv:property sv:name="hippo:sequence" sv:type="Double">
      <sv:value>30156.0</sv:value>
    </sv:property>
    <sv:property sv:name="hippo:contentresource" sv:type="String">
      <sv:value>hstconfiguration/taxonomydemo-fr/sitemap.xml</sv:value>
    </sv:property>
    <sv:property sv:name="hippo:contentroot" sv:type="String">
      <sv:value>/hst:hst/hst:configurations/taxonomydemo-fr</sv:value>
    </sv:property>
  </sv:node>
  <sv:node sv:name="taxonomydemo-fr-sitemenus">
    <sv:property sv:name="jcr:primaryType" sv:type="Name">
      <sv:value>hippo:initializeitem</sv:value>
    </sv:property>
    <sv:property sv:name="hippo:sequence" sv:type="Double">
      <sv:value>30157.0</sv:value>
    </sv:property>
    <sv:property sv:name="hippo:contentresource" sv:type="String">
      <sv:value>hstconfiguration/taxonomydemo-fr/sitemenus.xml</sv:value>
    </sv:property>
    <sv:property sv:name="hippo:contentroot" sv:type="String">
      <sv:value>/hst:hst/hst:configurations/taxonomydemo-fr</sv:value>
    </sv:property>
  </sv:node>
  <sv:node sv:name="taxonomydemo-fr-channel">
    <sv:property sv:name="jcr:primaryType" sv:type="Name">
      <sv:value>hippo:initializeitem</sv:value>
    </sv:property>
    <sv:property sv:name="hippo:sequence" sv:type="Double">
      <sv:value>30158.0</sv:value>
    </sv:property>
    <sv:property sv:name="hippo:contentresource" sv:type="String">
      <sv:value>hstconfiguration/taxonomydemo-fr/channel.xml</sv:value>
    </sv:property>
    <sv:property sv:name="hippo:contentroot" sv:type="String">
      <sv:value>/hst:hst/hst:configurations/taxonomydemo-fr</sv:value>
    </sv:property>
  </sv:node>
  <sv:node sv:name="taxonomydemo-nl-sitemap">
    <sv:property sv:name="jcr:primaryType" sv:type="Name">
      <sv:value>hippo:initializeitem</sv:value>
    </sv:property>
    <sv:property sv:name="hippo:sequence" sv:type="Double">
      <sv:value>30156.0</sv:value>
    </sv:property>
    <sv:property sv:name="hippo:contentresource" sv:type="String">
      <sv:value>hstconfiguration/taxonomydemo-nl/sitemap.xml</sv:value>
    </sv:property>
    <sv:property sv:name="hippo:contentroot" sv:type="String">
      <sv:value>/hst:hst/hst:configurations/taxonomydemo-nl</sv:value>
    </sv:property>
  </sv:node>
  <sv:node sv:name="taxonomydemo-nl-sitemenus">
    <sv:property sv:name="jcr:primaryType" sv:type="Name">
      <sv:value>hippo:initializeitem</sv:value>
    </sv:property>
    <sv:property sv:name="hippo:sequence" sv:type="Double">
      <sv:value>30157.0</sv:value>
    </sv:property>
    <sv:property sv:name="hippo:contentresource" sv:type="String">
      <sv:value>hstconfiguration/taxonomydemo-nl/sitemenus.xml</sv:value>
    </sv:property>
    <sv:property sv:name="hippo:contentroot" sv:type="String">
      <sv:value>/hst:hst/hst:configurations/taxonomydemo-nl</sv:value>
    </sv:property>
  </sv:node>
  <sv:node sv:name="taxonomydemo-nl-channel">
    <sv:property sv:name="jcr:primaryType" sv:type="Name">
      <sv:value>hippo:initializeitem</sv:value>
    </sv:property>
    <sv:property sv:name="hippo:sequence" sv:type="Double">
      <sv:value>30158.0</sv:value>
    </sv:property>
    <sv:property sv:name="hippo:contentresource" sv:type="String">
      <sv:value>hstconfiguration/taxonomydemo-nl/channel.xml</sv:value>
    </sv:property>
    <sv:property sv:name="hippo:contentroot" sv:type="String">
      <sv:value>/hst:hst/hst:configurations/taxonomydemo-nl</sv:value>
    </sv:property>
  </sv:node>
  <sv:node sv:name="conf-pages">
    <sv:property sv:name="jcr:primaryType" sv:type="Name">
      <sv:value>hippo:initializeitem</sv:value>
    </sv:property>
    <sv:property sv:name="hippo:sequence" sv:type="Double">
      <sv:value>30158.0</sv:value>
    </sv:property>
    <sv:property sv:name="hippo:contentresource" sv:type="String">
      <sv:value>hstconfiguration/pages.xml</sv:value>
    </sv:property>
    <sv:property sv:name="hippo:contentroot" sv:type="String">
      <sv:value>/hst:hst/hst:configurations/taxonomydemo-common</sv:value>
    </sv:property>
  </sv:node>
  <sv:node sv:name="conf-components">
    <sv:property sv:name="jcr:primaryType" sv:type="Name">
      <sv:value>hippo:initializeitem</sv:value>
    </sv:property>
    <sv:property sv:name="hippo:sequence" sv:type="Double">
      <sv:value>30159.0</sv:value>
    </sv:property>
    <sv:property sv:name="hippo:contentresource" sv:type="String">
      <sv:value>hstconfiguration/components.xml</sv:value>
    </sv:property>
    <sv:property sv:name="hippo:contentroot" sv:type="String">
      <sv:value>/hst:hst/hst:configurations/taxonomydemo-common</sv:value>
    </sv:property>
  </sv:node>
  <sv:node sv:name="conf-templates">
    <sv:property sv:name="jcr:primaryType" sv:type="Name">
      <sv:value>hippo:initializeitem</sv:value>
    </sv:property>
    <sv:property sv:name="hippo:sequence" sv:type="Double">
      <sv:value>30160.0</sv:value>
    </sv:property>
    <sv:property sv:name="hippo:contentresource" sv:type="String">
      <sv:value>hstconfiguration/templates.xml</sv:value>
    </sv:property>
    <sv:property sv:name="hippo:contentroot" sv:type="String">
      <sv:value>/hst:hst/hst:configurations/taxonomydemo-common</sv:value>
    </sv:property>
  </sv:node>
  <!-- Content -->
  <sv:node sv:name="taxonomydemo-root-en">
    <sv:property sv:name="jcr:primaryType" sv:type="Name">
      <sv:value>hippo:initializeitem</sv:value>
    </sv:property>
    <sv:property sv:name="hippo:sequence" sv:type="Double">
      <sv:value>30400.0</sv:value>
    </sv:property>
    <sv:property sv:name="hippo:contentresource" sv:type="String">
      <sv:value>taxonomy-demo-root-en.xml</sv:value>
    </sv:property>
    <sv:property sv:name="hippo:contentroot" sv:type="String">
      <sv:value>/content/documents</sv:value>
    </sv:property>
  </sv:node>
  <sv:node sv:name="taxonomydemo-root-fr">
    <sv:property sv:name="jcr:primaryType" sv:type="Name">
      <sv:value>hippo:initializeitem</sv:value>
    </sv:property>
    <sv:property sv:name="hippo:sequence" sv:type="Double">
      <sv:value>30400.0</sv:value>
    </sv:property>
    <sv:property sv:name="hippo:contentresource" sv:type="String">
      <sv:value>taxonomy-demo-root-fr.xml</sv:value>
    </sv:property>
    <sv:property sv:name="hippo:contentroot" sv:type="String">
      <sv:value>/content/documents</sv:value>
    </sv:property>
  </sv:node>
  <sv:node sv:name="taxonomydemo-root-nl">
    <sv:property sv:name="jcr:primaryType" sv:type="Name">
      <sv:value>hippo:initializeitem</sv:value>
    </sv:property>
    <sv:property sv:name="hippo:sequence" sv:type="Double">
      <sv:value>30400.0</sv:value>
    </sv:property>
    <sv:property sv:name="hippo:contentresource" sv:type="String">
      <sv:value>taxonomy-demo-root-nl.xml</sv:value>
    </sv:property>
    <sv:property sv:name="hippo:contentroot" sv:type="String">
      <sv:value>/content/documents</sv:value>
    </sv:property>
  </sv:node>
  <sv:node sv:name="taxonomydemo-common-en">
    <sv:property sv:name="jcr:primaryType" sv:type="Name">
      <sv:value>hippo:initializeitem</sv:value>
    </sv:property>
    <sv:property sv:name="hippo:sequence" sv:type="Double">
      <sv:value>30404.0</sv:value>
    </sv:property>
    <sv:property sv:name="hippo:contentresource" sv:type="String">
      <sv:value>taxonomy-demo-common-en.xml</sv:value>
    </sv:property>
    <sv:property sv:name="hippo:contentroot" sv:type="String">
      <sv:value>/content/documents/taxonomydemo</sv:value>
    </sv:property>
  </sv:node>
  <sv:node sv:name="taxonomydemo-common-fr">
    <sv:property sv:name="jcr:primaryType" sv:type="Name">
      <sv:value>hippo:initializeitem</sv:value>
    </sv:property>
    <sv:property sv:name="hippo:sequence" sv:type="Double">
      <sv:value>30404.0</sv:value>
    </sv:property>
    <sv:property sv:name="hippo:contentresource" sv:type="String">
      <sv:value>taxonomy-demo-common-fr.xml</sv:value>
    </sv:property>
    <sv:property sv:name="hippo:contentroot" sv:type="String">
      <sv:value>/content/documents/taxonomydemo-fr</sv:value>
    </sv:property>
  </sv:node>
  <sv:node sv:name="taxonomydemo-common-nl">
    <sv:property sv:name="jcr:primaryType" sv:type="Name">
      <sv:value>hippo:initializeitem</sv:value>
    </sv:property>
    <sv:property sv:name="hippo:sequence" sv:type="Double">
      <sv:value>30404.0</sv:value>
    </sv:property>
    <sv:property sv:name="hippo:contentresource" sv:type="String">
      <sv:value>taxonomy-demo-common-nl.xml</sv:value>
    </sv:property>
    <sv:property sv:name="hippo:contentroot" sv:type="String">
      <sv:value>/content/documents/taxonomydemo-nl</sv:value>
    </sv:property>
  </sv:node>
  <sv:node sv:name="taxonomies">
    <sv:property sv:name="jcr:primaryType" sv:type="Name">
      <sv:value>hippo:initializeitem</sv:value>
    </sv:property>
    <sv:property sv:name="hippo:sequence" sv:type="Double">
      <sv:value>30406.0</sv:value>
    </sv:property>
    <sv:property sv:name="hippo:contentresource" sv:type="String">
      <sv:value>taxonomies.xml</sv:value>
    </sv:property>
    <sv:property sv:name="hippo:contentroot" sv:type="String">
      <sv:value>/content</sv:value>
    </sv:property>
  </sv:node>
  <!-- /Content -->
  <sv:node sv:name="virtualhosts">
    <sv:property sv:name="jcr:primaryType" sv:type="Name">
      <sv:value>hippo:initializeitem</sv:value>
    </sv:property>
    <sv:property sv:name="hippo:sequence" sv:type="Double">
      <sv:value>31062.0</sv:value>
    </sv:property>
    <sv:property sv:name="hippo:contentresource" sv:type="String">
      <sv:value>hst-virtualhosts.xml</sv:value>
    </sv:property>
    <sv:property sv:name="hippo:contentroot" sv:type="String">
      <sv:value>/hst:hst</sv:value>
    </sv:property>
  </sv:node>
  <sv:node sv:name="taxonomydemo-allow-editor">
    <sv:property sv:name="jcr:primaryType" sv:type="Name">
      <sv:value>hippo:initializeitem</sv:value>
    </sv:property>
    <sv:property sv:name="hippo:sequence" sv:type="Double">
      <sv:value>30163.0</sv:value>
    </sv:property>
    <sv:property sv:name="hippo:contentresource" sv:type="String">
      <sv:value>taxonomy-allow-editor.xml</sv:value>
    </sv:property>
    <sv:property sv:name="hippo:contentdelete" sv:type="String">
      <sv:value>/hippo:configuration/hippo:domains/taxonomy/hippo:authrole</sv:value>
    </sv:property>
    <sv:property sv:name="hippo:contentroot" sv:type="String">
      <sv:value>/hippo:configuration/hippo:domains/taxonomy</sv:value>
    </sv:property>
  </sv:node>
  <!-- Security and default available users -->
  <sv:node sv:name="taxonomydemo-user-editor">
    <sv:property sv:name="jcr:primaryType" sv:type="Name">
      <sv:value>hippo:initializeitem</sv:value>
    </sv:property>
    <sv:property sv:name="hippo:contentresource" sv:type="String">
      <sv:value>security/user-editor.xml</sv:value>
    </sv:property>
    <sv:property sv:name="hippo:contentroot" sv:type="String">
      <sv:value>/hippo:configuration/hippo:users</sv:value>
    </sv:property>
    <sv:property sv:name="hippo:sequence" sv:type="Double">
      <sv:value>33000.0</sv:value>
    </sv:property>
  </sv:node>
  <sv:node sv:name="taxonomydemo-user-author">
    <sv:property sv:name="jcr:primaryType" sv:type="Name">
      <sv:value>hippo:initializeitem</sv:value>
    </sv:property>
    <sv:property sv:name="hippo:contentresource" sv:type="String">
      <sv:value>security/user-author.xml</sv:value>
    </sv:property>
    <sv:property sv:name="hippo:contentroot" sv:type="String">
      <sv:value>/hippo:configuration/hippo:users</sv:value>
    </sv:property>
    <sv:property sv:name="hippo:sequence" sv:type="Double">
      <sv:value>33100.1</sv:value>
    </sv:property>
  </sv:node>
  <sv:node sv:name="taxonomydemo-user-liveuser">
    <sv:property sv:name="jcr:primaryType" sv:type="Name">
      <sv:value>hippo:initializeitem</sv:value>
    </sv:property>
    <sv:property sv:name="hippo:contentresource" sv:type="String">
      <sv:value>security/user-liveuser.xml</sv:value>
    </sv:property>
    <sv:property sv:name="hippo:contentroot" sv:type="String">
      <sv:value>/hippo:configuration/hippo:users</sv:value>
    </sv:property>
    <sv:property sv:name="hippo:sequence" sv:type="Double">
      <sv:value>33100.2</sv:value>
    </sv:property>
  </sv:node>
  <sv:node sv:name="taxonomydemo-user-previewuser">
    <sv:property sv:name="jcr:primaryType" sv:type="Name">
      <sv:value>hippo:initializeitem</sv:value>
    </sv:property>
    <sv:property sv:name="hippo:contentresource" sv:type="String">
      <sv:value>security/user-previewuser.xml</sv:value>
    </sv:property>
    <sv:property sv:name="hippo:contentroot" sv:type="String">
      <sv:value>/hippo:configuration/hippo:users</sv:value>
    </sv:property>
    <sv:property sv:name="hippo:sequence" sv:type="Double">
      <sv:value>33100.2</sv:value>
    </sv:property>
  </sv:node>
  <sv:node sv:name="taxonomydemo-user-configuser">
    <sv:property sv:name="jcr:primaryType" sv:type="Name">
      <sv:value>hippo:initializeitem</sv:value>
    </sv:property>
    <sv:property sv:name="hippo:contentresource" sv:type="String">
      <sv:value>security/user-configuser.xml</sv:value>
    </sv:property>
    <sv:property sv:name="hippo:contentroot" sv:type="String">
      <sv:value>/hippo:configuration/hippo:users</sv:value>
    </sv:property>
    <sv:property sv:name="hippo:sequence" sv:type="Double">
      <sv:value>33100.2</sv:value>
    </sv:property>
  </sv:node>
  <sv:node sv:name="taxonomydemo-user-sitewriter">
    <sv:property sv:name="jcr:primaryType" sv:type="Name">
      <sv:value>hippo:initializeitem</sv:value>
    </sv:property>
    <sv:property sv:name="hippo:contentresource" sv:type="String">
      <sv:value>security/user-sitewriter.xml</sv:value>
    </sv:property>
    <sv:property sv:name="hippo:contentroot" sv:type="String">
      <sv:value>/hippo:configuration/hippo:users</sv:value>
    </sv:property>
    <sv:property sv:name="hippo:sequence" sv:type="Double">
      <sv:value>33100.2</sv:value>
    </sv:property>
  </sv:node>
  <sv:node sv:name="taxonomydemo-groups-author-add">
    <sv:property sv:name="jcr:primaryType" sv:type="Name">
      <sv:value>hippo:initializeitem</sv:value>
    </sv:property>
    <sv:property sv:name="hippo:contentpropadd" sv:type="String">
      <sv:value>author</sv:value>
    </sv:property>
    <sv:property sv:name="hippo:contentroot" sv:type="String">
      <sv:value>/hippo:configuration/hippo:groups/author/hipposys:members</sv:value>
    </sv:property>
    <sv:property sv:name="hippo:sequence" sv:type="Double">
      <sv:value>33100.3</sv:value>
    </sv:property>
  </sv:node>
  <sv:node sv:name="taxonomydemo-groups-editor-add">
    <sv:property sv:name="jcr:primaryType" sv:type="Name">
      <sv:value>hippo:initializeitem</sv:value>
    </sv:property>
    <sv:property sv:name="hippo:contentpropadd" sv:type="String">
      <sv:value>editor</sv:value>
    </sv:property>
    <sv:property sv:name="hippo:contentroot" sv:type="String">
      <sv:value>/hippo:configuration/hippo:groups/editor/hipposys:members</sv:value>
    </sv:property>
    <sv:property sv:name="hippo:sequence" sv:type="Double">
      <sv:value>33100.4</sv:value>
    </sv:property>
  </sv:node>
  <sv:node sv:name="taxonomydemo-groups-webmaster-add">
    <sv:property sv:name="jcr:primaryType" sv:type="Name">
      <sv:value>hippo:initializeitem</sv:value>
    </sv:property>
    <sv:property sv:name="hippo:contentroot" sv:type="String">
      <sv:value>/hippo:configuration/hippo:groups/webmaster/hipposys:members</sv:value>
    </sv:property>
    <sv:property sv:name="hippo:sequence" sv:type="Double">
      <sv:value>33100.5</sv:value>
    </sv:property>
    <sv:property sv:multiple="true" sv:name="hippo:contentpropadd" sv:type="String">
      <sv:value>editor</sv:value>
    </sv:property>
  </sv:node>
  <sv:node sv:name="taxonomydemo-group-sitewriters">
    <sv:property sv:name="jcr:primaryType" sv:type="Name">
      <sv:value>hippo:initializeitem</sv:value>
    </sv:property>
    <sv:property sv:name="hippo:contentresource" sv:type="String">
      <sv:value>security/group-sitewriters.xml</sv:value>
    </sv:property>
    <sv:property sv:name="hippo:contentroot" sv:type="String">
      <sv:value>/hippo:configuration/hippo:groups</sv:value>
    </sv:property>
    <sv:property sv:name="hippo:sequence" sv:type="Double">
      <sv:value>33100.6</sv:value>
    </sv:property>
  </sv:node>
  <sv:node sv:name="taxonomydemo-group-liveusers">
    <sv:property sv:name="jcr:primaryType" sv:type="Name">
      <sv:value>hippo:initializeitem</sv:value>
    </sv:property>
    <sv:property sv:name="hippo:contentresource" sv:type="String">
      <sv:value>security/group-liveusers.xml</sv:value>
    </sv:property>
    <sv:property sv:name="hippo:contentroot" sv:type="String">
      <sv:value>/hippo:configuration/hippo:groups</sv:value>
    </sv:property>
    <sv:property sv:name="hippo:sequence" sv:type="Double">
      <sv:value>33100.6</sv:value>
    </sv:property>
  </sv:node>
  <sv:node sv:name="taxonomydemo-group-previewusers">
    <sv:property sv:name="jcr:primaryType" sv:type="Name">
      <sv:value>hippo:initializeitem</sv:value>
    </sv:property>
    <sv:property sv:name="hippo:contentresource" sv:type="String">
      <sv:value>security/group-previewusers.xml</sv:value>
    </sv:property>
    <sv:property sv:name="hippo:contentroot" sv:type="String">
      <sv:value>/hippo:configuration/hippo:groups</sv:value>
    </sv:property>
    <sv:property sv:name="hippo:sequence" sv:type="Double">
      <sv:value>33100.6</sv:value>
    </sv:property>
  </sv:node>
  <sv:node sv:name="taxonomydemo-sitewriters-readfolders">
    <sv:property sv:name="jcr:primaryType" sv:type="Name">
      <sv:value>hippo:initializeitem</sv:value>
    </sv:property>
    <sv:property sv:name="hippo:contentpropadd" sv:type="String">
      <sv:value>sitewriters</sv:value>
    </sv:property>
    <sv:property sv:name="hippo:contentroot" sv:type="String">
      <sv:value>/hippo:configuration/hippo:domains/hippofolders/readonly/hipposys:groups</sv:value>
    </sv:property>
    <sv:property sv:name="hippo:sequence" sv:type="Double">
      <sv:value>33100.7</sv:value>
    </sv:property>
  </sv:node>
  <sv:node sv:name="taxonomydemo-previewusers-documents">
    <sv:property sv:name="jcr:primaryType" sv:type="Name">
      <sv:value>hippo:initializeitem</sv:value>
    </sv:property>
    <sv:property sv:name="hippo:contentpropadd" sv:type="String">
      <sv:value>previewusers</sv:value>
    </sv:property>
    <sv:property sv:name="hippo:contentroot" sv:type="String">
      <sv:value>/hippo:configuration/hippo:domains/preview-documents/readonly/hipposys:groups</sv:value>
    </sv:property>
    <sv:property sv:name="hippo:sequence" sv:type="Double">
      <sv:value>33100.7</sv:value>
    </sv:property>
  </sv:node>
  <sv:node sv:name="taxonomydemo-liveusers-documents">
    <sv:property sv:name="jcr:primaryType" sv:type="Name">
      <sv:value>hippo:initializeitem</sv:value>
    </sv:property>
    <sv:property sv:name="hippo:contentpropadd" sv:type="String">
      <sv:value>liveusers</sv:value>
    </sv:property>
    <sv:property sv:name="hippo:contentroot" sv:type="String">
      <sv:value>/hippo:configuration/hippo:domains/live-documents/readonly/hipposys:groups</sv:value>
    </sv:property>
    <sv:property sv:name="hippo:sequence" sv:type="Double">
      <sv:value>33100.7</sv:value>
    </sv:property>
  </sv:node>
  <sv:node sv:name="taxonomydemo-configuser-read-everywhere">
    <sv:property sv:name="jcr:primaryType" sv:type="Name">
      <sv:value>hippo:initializeitem</sv:value>
    </sv:property>
    <sv:property sv:name="hippo:contentresource" sv:type="String">
      <sv:value>security/configuser-read-everywhere.xml</sv:value>
    </sv:property>
    <sv:property sv:name="hippo:contentroot" sv:type="String">
      <sv:value>/hippo:configuration/hippo:domains/everywhere</sv:value>
    </sv:property>
    <sv:property sv:name="hippo:sequence" sv:type="Double">
      <sv:value>33100.7</sv:value>
    </sv:property>
  </sv:node>
  <!-- Autoexport module configuration -->
  <sv:node sv:name="taxonomydemo-autoexport-module">
    <sv:property sv:name="jcr:primaryType" sv:type="Name">
      <sv:value>hippo:initializeitem</sv:value>
    </sv:property>
    <sv:property sv:name="hippo:contentresource" sv:type="String">
      <sv:value>configuration/modules/autoexport-module.xml</sv:value>
    </sv:property>
    <sv:property sv:name="hippo:contentroot" sv:type="String">
      <sv:value>/hippo:configuration/hippo:modules</sv:value>
    </sv:property>
    <sv:property sv:name="hippo:sequence" sv:type="Double">
      <sv:value>30010</sv:value>
    </sv:property>
  </sv:node>

  <!-- add service for extra taxonomy -->
  <sv:node sv:name="hippo-configuration-hippo-frontend-cms-services-alternateClassificationDaoService">
    <sv:property sv:name="jcr:primaryType" sv:type="Name">
      <sv:value>hippo:initializeitem</sv:value>
    </sv:property>
    <sv:property sv:name="hippo:sequence" sv:type="Double">
      <sv:value>30000.3</sv:value>
    </sv:property>
    <sv:property sv:name="hippo:contentresource" sv:type="String">
      <sv:value>cms-services/alternateClassificationDaoService.xml</sv:value>
    </sv:property>
    <sv:property sv:name="hippo:contentroot" sv:type="String">
      <sv:value>/hippo:configuration/hippo:frontend/cms/cms-services</sv:value>
    </sv:property>
  </sv:node>
  <sv:node sv:name="taxonomydemo-translations">
    <sv:property sv:name="jcr:primaryType" sv:type="Name">
      <sv:value>hippo:initializeitem</sv:value>
    </sv:property>
    <sv:property sv:name="hippo:sequence" sv:type="Double">
      <sv:value>30150.1</sv:value>
    </sv:property>
    <sv:property sv:name="hippo:resourcebundles" sv:type="String">
      <sv:value>translations.json</sv:value>
    </sv:property>
  </sv:node>
</sv:node>
